mindconnectiot/__init__.py
mindconnectiot/mindconnectiot.py
mindconnectiot-0.1.8.dist-info/LICENSE
mindconnectiot-0.1.8.dist-info/METADATA
mindconnectiot-0.1.8.dist-info/WHEEL
mindconnectiot-0.1.8.dist-info/top_level.txt
mindconnectiot-0.1.8.dist-info/RECORD
