Metadata-Version: 2.1
Name: mindconnectiot
Version: 0.1.8
Summary: Wrapper around the MindConnect IoT Extention.
Home-page: https://gitlab.com/Addono/mindconnect-iot-extension-python
Author: Adriaan Knapen
Author-email: hi@aknapen.nl
License: MIT
Platform: UNKNOWN
Classifier: License :: OSI Approved :: MIT License
Classifier: Programming Language :: Python :: 3
Classifier: Programming Language :: Python :: 3.7
Requires-Dist: paho-mqtt
